{
    "name": "dummy-project",
    "build": {
        "context": "../..",
        "dockerfile": "../../dummy_project/Dockerfile"
    },
    "workspaceFolder": "/workspace",
    "workspaceMount": "source=${localWorkspaceFolder},target=/workspace,type=bind,consistency=cached",
    "remoteUser": "devuser",
    "customizations": {
        "vscode": {
            "extensions": [
                "ms-vscode.cpptools",
                "ms-vscode.cmake-tools",
                "ms-python.python",
                "charliermarsh.ruff",
                "ms-toolsai.jupyter"
            ],
            "settings": {
                "python.defaultInterpreterPath": "/workspace/.venv/bin/python",
                "python.venvPath": "/workspace"
            }
        }
    },
    "postCreateCommand": "cd dummy_project && uv sync && cd /workspace && bash scripts/setup.sh"
}
